aider_mbpy/__about__.py
aider_mbpy/__init__.py
aider_mbpy/cli.py
aider_mbpy-0.0.1.dist-info/METADATA
aider_mbpy-0.0.1.dist-info/WHEEL
aider_mbpy-0.0.1.dist-info/entry_points.txt
aider_mbpy-0.0.1.dist-info/licenses/LICENSE.txt
aider_mbpy-0.0.1.dist-info/RECORD
